speechbrain/__init__.py
speechbrain/core.py
speechbrain/log-config.yaml
speechbrain/version.txt
speechbrain/alignment/__init__.py
speechbrain/alignment/aligner.py
speechbrain/alignment/ctc_segmentation.py
speechbrain/augment/__init__.py
speechbrain/augment/augmenter.py
speechbrain/augment/codec.py
speechbrain/augment/freq_domain.py
speechbrain/augment/preparation.py
speechbrain/augment/time_domain.py
speechbrain/dataio/__init__.py
speechbrain/dataio/batch.py
speechbrain/dataio/dataio.py
speechbrain/dataio/dataloader.py
speechbrain/dataio/dataset.py
speechbrain/dataio/encoder.py
speechbrain/dataio/iterators.py
speechbrain/dataio/legacy.py
speechbrain/dataio/preprocess.py
speechbrain/dataio/sampler.py
speechbrain/dataio/wer.py
speechbrain/decoders/__init__.py
speechbrain/decoders/ctc.py
speechbrain/decoders/language_model.py
speechbrain/decoders/scorer.py
speechbrain/decoders/seq2seq.py
speechbrain/decoders/transducer.py
speechbrain/decoders/utils.py
speechbrain/inference/ASR.py
speechbrain/inference/SLU.py
speechbrain/inference/ST.py
speechbrain/inference/TTS.py
speechbrain/inference/VAD.py
speechbrain/inference/__init__.py
speechbrain/inference/classifiers.py
speechbrain/inference/diarization.py
speechbrain/inference/encoders.py
speechbrain/inference/enhancement.py
speechbrain/inference/interfaces.py
speechbrain/inference/interpretability.py
speechbrain/inference/metrics.py
speechbrain/inference/separation.py
speechbrain/inference/speaker.py
speechbrain/inference/text.py
speechbrain/inference/vocoders.py
speechbrain/k2_integration/__init__.py
speechbrain/k2_integration/graph_compiler.py
speechbrain/k2_integration/lattice_decoder.py
speechbrain/k2_integration/lexicon.py
speechbrain/k2_integration/losses.py
speechbrain/k2_integration/prepare_lang.py
speechbrain/k2_integration/utils.py
speechbrain/lm/__init__.py
speechbrain/lm/arpa.py
speechbrain/lm/counting.py
speechbrain/lm/ngram.py
speechbrain/lobes/__init__.py
speechbrain/lobes/beamform_multimic.py
speechbrain-1.0.2.dist-info/LICENSE
speechbrain-1.0.2.dist-info/METADATA
speechbrain-1.0.2.dist-info/WHEEL
speechbrain-1.0.2.dist-info/top_level.txt
speechbrain-1.0.2.dist-info/RECORD
