Metadata-Version: 2.1
Name: speechbrain
Version: 1.0.2
Summary: All-in-one speech toolkit in pure Python and Pytorch
Home-page: https://speechbrain.github.io/
Author: Mirco Ravanelli, Titouan Parcollet & Others
Author-email: speechbrain@gmail.com
Classifier: Programming Language :: Python :: 3
Classifier: License :: OSI Approved :: Apache Software License
Requires-Python: >=3.8
License-File: LICENSE
Requires-Dist: hyperpyyaml
Requires-Dist: joblib
Requires-Dist: numpy
Requires-Dist: packaging
Requires-Dist: scipy
Requires-Dist: sentencepiece
Requires-Dist: torch>=1.9
Requires-Dist: torchaudio
Requires-Dist: tqdm
Requires-Dist: huggingface_hub
